setup.py
tests/__init__.py
vtex_client/__init__.py
vtex_client/base.py
vtex_client/card.py
vtex_client/faults.py
vtex_client/transaction.py
vtex_client.egg-info/PKG-INFO
vtex_client.egg-info/SOURCES.txt
vtex_client.egg-info/dependency_links.txt
vtex_client.egg-info/namespace_packages.txt
vtex_client.egg-info/requires.txt
vtex_client.egg-info/top_level.txt