Metadata-Version: 1.1
Name: vtex-client
Version: 0.1.0
Summary: Client to consume the VTEX payment gateway API
Home-page: https://github.com/Onyo/vtex-client
Author: Onyo Inc (onyo.com)
Author-email: backend@onyo.com
License: MIT License
Download-URL: https://github.com/Onyo/vtex-client/tarball/master
Keywords: vtex_client
Platform: UNKNOWN
Classifier: Development Status :: 4 - Beta
Classifier: Topic :: Utilities
Classifier: Environment :: Plugins
Classifier: License :: OSI Approved :: MIT License
Classifier: Operating System :: OS Independent
Classifier: Intended Audience :: Developers
